gc_count-0.2.1.dist-info/METADATA
gc_count-0.2.1.dist-info/WHEEL
gc_count/__init__.py
gc_count/__init__.pyi
gc_count/py.typed
gc_count/gc_count.cpython-310-darwin.so
gc_count-0.2.1.dist-info/RECORD
